python_lei/__init__.py
python_lei/exceptions.py
python_lei/isin_lei.py
python_lei/lei_search.py
python_lei/parser.py
python_lei/pylei.py
python_lei/utils.py
python_lei-0.1.1.dist-info/LICENSE.md
python_lei-0.1.1.dist-info/METADATA
python_lei-0.1.1.dist-info/WHEEL
python_lei-0.1.1.dist-info/top_level.txt
python_lei-0.1.1.dist-info/RECORD
