Metadata-Version: 2.1
Name: python-lei
Version: 0.1.1
Summary: Python wraper for Legal Entity Identification API and ISIN to LEI and vice versa conversion.
Home-page: https://github.com/jdvala/python-lei
Author: jdvala
Author-email: jay.vala@msn.com
License: MIT
Keywords: LEI python-lei Legal-Entity-Identification ISIN Finance Business LEI-code Leilex
Platform: UNKNOWN
Classifier: Development Status :: 5 - Production/Stable
Classifier: Intended Audience :: Developers
Classifier: License :: OSI Approved :: MIT License
Classifier: Operating System :: OS Independent
Classifier: Programming Language :: Python :: 3.5
Classifier: Programming Language :: Python :: 3.6
Classifier: Programming Language :: Python :: 3.7
Classifier: Programming Language :: Python :: 3.8
Classifier: Topic :: Software Development :: Libraries :: Python Modules
Classifier: Topic :: Utilities
Requires-Python: >=3.5
Requires-Dist: pandas
Requires-Dist: texttable
Requires-Dist: requests
